uni_say/__init__.py
uni_say/cli.py
uni_say-0.1.12.dist-info/entry_points.txt
uni_say-0.1.12.dist-info/WHEEL
uni_say-0.1.12.dist-info/METADATA
uni_say-0.1.12.dist-info/RECORD
